{
  "logging": {
    "logs": {
      "default": {
        "level": "DEBUG"
      }
    }
  },
  "apps": {
    "http": {
      "https_port": 3443,
      "servers": {
        "srv0": {
          "listen": [
            ":3443"
          ],
          "routes": [
            {
              "handle": [
                {
                  "handler": "authentication",
                  "providers": {
                    "jwt": {
                      "token_name": "access_token",
                      "token_secret": "383aca9a-1c39-4d7a-b4d8-67ba4718dd3f",
                      "token_issuer": "7a50e023-2c6e-4a5e-913e-23ecd0e2b940",
                      "auth_url_path": "/login",
                      "access_list": [
                        {
                          "action": "allow",
                          "claim": "roles",
                          "values": [
                            "AzureAD_Viewer",
                            "AzureAD_Editor",
                            "AzureAD_Administrator"
                          ]
                        }
                      ],
                      "strip_token": false,
                      "pass_claims": false,
                      "token_types": [
                        "HS256",
                        "HS384",
                        "HS512",
                        "RS256",
                        "RS384",
                        "RS512",
                        "ES256",
                        "ES384",
                        "ES512"
                      ],
                      "token_sources": [
                        "header",
                        "cookie",
                        "query"
                      ]
                    }
                  }
                },
                {
                  "body": "OK",
                  "handler": "static_response",
                  "status_code": 200
                }
              ],
              "match": [
                {
                  "path": [
                    "/health"
                  ]
                }
              ],
              "terminal": true
            },
            {
              "handle": [
                {
                  "handler": "authentication",
                  "providers": {
                    "jwt": {
                      "token_name": "access_token",
                      "token_secret": "383aca9a-1c39-4d7a-b4d8-67ba4718dd3f",
                      "token_issuer": "7a50e023-2c6e-4a5e-913e-23ecd0e2b940",
                      "auth_url_path": "/login",
                      "access_list": [
                        {
                          "action": "allow",
                          "claim": "roles",
                          "values": [
                            "AzureAD_Viewer",
                            "AzureAD_Editor",
                            "AzureAD_Administrator"
                          ]
                        }
                      ],
                      "strip_token": false,
                      "pass_claims": false,
                      "token_types": [
                        "HS256",
                        "HS384",
                        "HS512",
                        "RS256",
                        "RS384",
                        "RS512",
                        "ES256",
                        "ES384",
                        "ES512"
                      ],
                      "token_sources": [
                        "header",
                        "cookie",
                        "query"
                      ]
                    }
                  }
                },
                {
                  "body": "OK",
                  "handler": "static_response",
                  "status_code": 200
                }
              ],
              "match": [
                {
                  "path": [
                    "/metrics"
                  ]
                }
              ],
              "terminal": true
            },
            {
              "handle": [
                {
                  "body": "1.0.0",
                  "handler": "static_response",
                  "status_code": 200
                }
              ],
              "match": [
                {
                  "path": [
                    "/version"
                  ]
                }
              ],
              "terminal": true
            }
          ],
          "tls_connection_policies": [
            {
              "certificate_selection": {
                "any_tag": [
                  "cert0"
                ]
              }
            }
          ]
        }
      }
    },
    "tls": {
      "certificates": {
        "load_files": [
          {
            "certificate": "/caddy.localhost.crt",
            "key": "/caddy.localhost.key",
            "tags": [
              "cert0"
            ]
          }
        ]
      }
    },
    "pki": {
      "certificate_authorities": {
        "local": {
          "install_trust": false
        }
      }
    }
  }
}
